{
  "Name": "Steven",
  "Class": "",
  "Level": "",
  "Race": "",
  "Experience_Points": "",
  "Proficiency_Bonus": "5",
  "Strength": "",
  "StrST": "",
  "Athletics": "",
  "Dexterity": "",
  "Dex_Saving_Throw": "",
  "Acrobatics": "",
  "Slight_of_Hand": "",
  "Stealth": "",
  "Constitution": "",
  "Con_Saving_Throw": "",
  "Intelligence": "",
  "Int_Saving_Throw": "",
  "Arcana": "",
  "History": "",
  "Investigation": "",
  "Nature": "",
  "Religion": "",
  "Wisdom": "",
  "Wis_Saving_Throw": "",
  "Animal_Handling": "",
  "Insight": "",
  "Medicine": "",
  "Perception": "",
  "Survival": "",
  "Charisma": "",
  "Chr_Saving_Throw": "",
  "Deception": "",
  "Intimidation": "",
  "Performance": "",
  "Persuasion": "",
  "PassiveWisdom": "",
  "ArmorClass": "11",
  "AC_Dexterity_Modifier": "1",
  "AC_Armor": "3",
  "AC_Shield": "3",
  "AC_Misc": "4",
  "Initiative": "8",
  "Speed": "",
  "Health_Maximum": "",
  "Current_Health": "",
  "Total_Hit_Dice": "",
  "Hit_Dice": "",
  "Weapon1": "",
  "Weapon1Range": "",
  "Weapon1Type": "",
  "Weapon1AttackBonus": "",
  "Weapon1Damage": "",
  "Weapon2": "",
  "Weapon2Range": "",
  "Weapon2Type": "",
  "Weapon2AttackBonus": "",
  "Weapon2Damage": "",
  "Weapon3": "",
  "Weapon3Range": "",
  "Weapon3Type": "",
  "Weapon3AttackBonus": "",
  "Weapon3Damage": "",
  "Items_Text_Box": "",
  "Items_Text_Box2": "",
  "Featires_Traits_Box": "This is a test to test if the text boxes can contain, save, and load all of the appropriate text contained within them.\nTest Test\n\n\nTest",
  "OtherProficienciesLanguages_Box": "",
  "StrengthProficiencyButton": 0,
  "AthleticsProficiencyButton": 0,
  "DexterityProcifiencyButton": 0,
  "AcrobaticsProficiencyButton": 0,
  "SoHProficiencyButton": 0,
  "StealthProficiencyButton": 0,
  "ConstitutionProficiencyButton": 0,
  "IntelligenceProficiencyButton": 0,
  "ArcanaProficiencyButton": 0,
  "HistoryProficiencyButton": 0,
  "InvestigationProficiencyButton": 0,
  "NatureProficiencyButton": 0,
  "ReligionProficiencyButton": 0,
  "WisdomProficiencyButton": 0,
  "AnimalHandlingProficiencyButton": 0,
  "InsightProficiencyButton": 0,
  "MedicineProficiencyButton": 0,
  "PerceptionProficiencyButton": 0,
  "SurvivalProficiencyButton": 0,
  "CharismaProficiencyButton": 0,
  "DeceptionProficiencyButton": 0,
  "IntimidationProficiencyButton": 0,
  "PerformanceProficiencyButton": 0,
  "PersuasionProficiencyButton": 0,
  "DeathSave1": 1,
  "DeathSave2": 0,
  "DeathSave3": 0,
  "DeathFail1": 1,
  "DeathFail2": 1,
  "DeathFail3": 0
}